[
  {
    "firstName": "Test",
    "lastName": "Owner1",
    "email": "owner1@owner.com",
    "password": "$2b$10$wO9ozl5LLGmLQBnA1FWv5.Mk8Q.FxFzeOwc7wZ9.O32XMaiLrn0wW"
  },
  {
    "firstName": "Test",
    "lastName": "Owner2",
    "email": "owner2@owner.com",
    "password": "$2b$10$wO9ozl5LLGmLQBnA1FWv5.Mk8Q.FxFzeOwc7wZ9.O32XMaiLrn0wW"
  },
  {
    "firstName": "Test",
    "lastName": "Owner3",
    "email": "owner3@owner.com",
    "password": "$2b$10$wO9ozl5LLGmLQBnA1FWv5.Mk8Q.FxFzeOwc7wZ9.O32XMaiLrn0wW"
  },
  {
    "firstName": "Test",
    "lastName": "Admin1",
    "email": "admin1@admin.com",
    "password": "$2b$10$wO9ozl5LLGmLQBnA1FWv5.Mk8Q.FxFzeOwc7wZ9.O32XMaiLrn0wW"
  },
  {
    "firstName": "Test",
    "lastName": "Admin2",
    "email": "admin2@admin.com",
    "password": "$2b$10$wO9ozl5LLGmLQBnA1FWv5.Mk8Q.FxFzeOwc7wZ9.O32XMaiLrn0wW"
  },
  {
    "firstName": "Test",
    "lastName": "Admin3",
    "email": "admin3@admin.com",
    "password": "$2b$10$wO9ozl5LLGmLQBnA1FWv5.Mk8Q.FxFzeOwc7wZ9.O32XMaiLrn0wW"
  },
  {
    "firstName": "Test",
    "lastName": "Admin4",
    "email": "admin4@admin.com",
    "password": "$2b$10$wO9ozl5LLGmLQBnA1FWv5.Mk8Q.FxFzeOwc7wZ9.O32XMaiLrn0wW"
  },
  {
    "firstName": "Test",
    "lastName": "Admin5",
    "email": "admin5@admin.com",
    "password": "$2b$10$wO9ozl5LLGmLQBnA1FWv5.Mk8Q.FxFzeOwc7wZ9.O32XMaiLrn0wW"
  },
  {
    "firstName": "Test",
    "lastName": "Admin6",
    "email": "admin6@admin.com",
    "password": "$2b$10$wO9ozl5LLGmLQBnA1FWv5.Mk8Q.FxFzeOwc7wZ9.O32XMaiLrn0wW"
  },
  {
    "firstName": "Test",
    "lastName": "User1",
    "email": "user1@user.com",
    "password": "$2b$10$wO9ozl5LLGmLQBnA1FWv5.Mk8Q.FxFzeOwc7wZ9.O32XMaiLrn0wW"
  },
  {
    "firstName": "Test",
    "lastName": "User2",
    "email": "user2@user.com",
    "password": "$2b$10$wO9ozl5LLGmLQBnA1FWv5.Mk8Q.FxFzeOwc7wZ9.O32XMaiLrn0wW"
  },
  {
    "firstName": "Test",
    "lastName": "User3",
    "email": "user3@user.com",
    "password": "$2b$10$wO9ozl5LLGmLQBnA1FWv5.Mk8Q.FxFzeOwc7wZ9.O32XMaiLrn0wW"
  },
  {
    "firstName": "Test",
    "lastName": "User4",
    "email": "user4@user.com",
    "password": "$2b$10$wO9ozl5LLGmLQBnA1FWv5.Mk8Q.FxFzeOwc7wZ9.O32XMaiLrn0wW"
  },
  {
    "firstName": "Test",
    "lastName": "User5",
    "email": "user5@user.com",
    "password": "$2b$10$wO9ozl5LLGmLQBnA1FWv5.Mk8Q.FxFzeOwc7wZ9.O32XMaiLrn0wW"
  },
  {
    "firstName": "Test",
    "lastName": "User6",
    "email": "user6@user.com",
    "password": "$2b$10$wO9ozl5LLGmLQBnA1FWv5.Mk8Q.FxFzeOwc7wZ9.O32XMaiLrn0wW"
  },
  {
    "firstName": "Test",
    "lastName": "User7",
    "email": "user7@user.com",
    "password": "$2b$10$wO9ozl5LLGmLQBnA1FWv5.Mk8Q.FxFzeOwc7wZ9.O32XMaiLrn0wW"
  },
  {
    "firstName": "Test",
    "lastName": "User8",
    "email": "user8@user.com",
    "password": "$2b$10$wO9ozl5LLGmLQBnA1FWv5.Mk8Q.FxFzeOwc7wZ9.O32XMaiLrn0wW"
  },
  {
    "firstName": "Test",
    "lastName": "User9",
    "email": "user9@user.com",
    "password": "$2b$10$wO9ozl5LLGmLQBnA1FWv5.Mk8Q.FxFzeOwc7wZ9.O32XMaiLrn0wW"
  },
  {
    "firstName": "Test",
    "lastName": "User10",
    "email": "user10@user.com",
    "password": "$2b$10$wO9ozl5LLGmLQBnA1FWv5.Mk8Q.FxFzeOwc7wZ9.O32XMaiLrn0wW"
  },
  {
    "firstName": "Test",
    "lastName": "User11",
    "email": "user11@user.com",
    "password": "$2b$10$wO9ozl5LLGmLQBnA1FWv5.Mk8Q.FxFzeOwc7wZ9.O32XMaiLrn0wW"
  },
  {
    "firstName": "Test",
    "lastName": "User12",
    "email": "user12@user.com",
    "password": "$2b$10$wO9ozl5LLGmLQBnA1FWv5.Mk8Q.FxFzeOwc7wZ9.O32XMaiLrn0wW"
  },
  {
    "firstName": "Test",
    "lastName": "User13",
    "email": "user13@user.com",
    "password": "$2b$10$wO9ozl5LLGmLQBnA1FWv5.Mk8Q.FxFzeOwc7wZ9.O32XMaiLrn0wW"
  },
  {
    "firstName": "Test",
    "lastName": "User14",
    "email": "user14@user.com",
    "password": "$2b$10$wO9ozl5LLGmLQBnA1FWv5.Mk8Q.FxFzeOwc7wZ9.O32XMaiLrn0wW"
  },
  {
    "firstName": "Test",
    "lastName": "User15",
    "email": "user15@user.com",
    "password": "$2b$10$wO9ozl5LLGmLQBnA1FWv5.Mk8Q.FxFzeOwc7wZ9.O32XMaiLrn0wW"
  },
  {
    "firstName": "Test",
    "lastName": "User16",
    "email": "user16@user.com",
    "password": "$2b$10$wO9ozl5LLGmLQBnA1FWv5.Mk8Q.FxFzeOwc7wZ9.O32XMaiLrn0wW"
  },
  {
    "firstName": "Test",
    "lastName": "User17",
    "email": "user17@user.com",
    "password": "$2b$10$wO9ozl5LLGmLQBnA1FWv5.Mk8Q.FxFzeOwc7wZ9.O32XMaiLrn0wW"
  },
  {
    "firstName": "Test",
    "lastName": "User18",
    "email": "user18@user.com",
    "password": "$2b$10$wO9ozl5LLGmLQBnA1FWv5.Mk8Q.FxFzeOwc7wZ9.O32XMaiLrn0wW"
  },
  {
    "firstName": "Test",
    "lastName": "User19",
    "email": "user19@user.com",
    "password": "$2b$10$wO9ozl5LLGmLQBnA1FWv5.Mk8Q.FxFzeOwc7wZ9.O32XMaiLrn0wW"
  },
  {
    "firstName": "Test",
    "lastName": "User20",
    "email": "user20@user.com",
    "password": "$2b$10$wO9ozl5LLGmLQBnA1FWv5.Mk8Q.FxFzeOwc7wZ9.O32XMaiLrn0wW"
  },
  {
    "firstName": "Test",
    "lastName": "User21",
    "email": "user21@user.com",
    "password": "$2b$10$wO9ozl5LLGmLQBnA1FWv5.Mk8Q.FxFzeOwc7wZ9.O32XMaiLrn0wW"
  },
  {
    "firstName": "Test",
    "lastName": "User22",
    "email": "user22@user.com",
    "password": "$2b$10$wO9ozl5LLGmLQBnA1FWv5.Mk8Q.FxFzeOwc7wZ9.O32XMaiLrn0wW"
  },
  {
    "firstName": "Test",
    "lastName": "User23",
    "email": "user23@user.com",
    "password": "$2b$10$wO9ozl5LLGmLQBnA1FWv5.Mk8Q.FxFzeOwc7wZ9.O32XMaiLrn0wW"
  },
  {
    "firstName": "Test",
    "lastName": "User24",
    "email": "user24@user.com",
    "password": "$2b$10$wO9ozl5LLGmLQBnA1FWv5.Mk8Q.FxFzeOwc7wZ9.O32XMaiLrn0wW"
  },
  {
    "firstName": "Test",
    "lastName": "User25",
    "email": "user25@user.com",
    "password": "$2b$10$wO9ozl5LLGmLQBnA1FWv5.Mk8Q.FxFzeOwc7wZ9.O32XMaiLrn0wW"
  },
  {
    "firstName": "Test",
    "lastName": "User26",
    "email": "user26@user.com",
    "password": "$2b$10$wO9ozl5LLGmLQBnA1FWv5.Mk8Q.FxFzeOwc7wZ9.O32XMaiLrn0wW"
  },
  {
    "firstName": "Test",
    "lastName": "User27",
    "email": "user27@user.com",
    "password": "$2b$10$wO9ozl5LLGmLQBnA1FWv5.Mk8Q.FxFzeOwc7wZ9.O32XMaiLrn0wW"
  },
  {
    "firstName": "Test",
    "lastName": "User28",
    "email": "user28@user.com",
    "password": "$2b$10$wO9ozl5LLGmLQBnA1FWv5.Mk8Q.FxFzeOwc7wZ9.O32XMaiLrn0wW"
  },
  {
    "firstName": "Test",
    "lastName": "User29",
    "email": "user29@user.com",
    "password": "$2b$10$wO9ozl5LLGmLQBnA1FWv5.Mk8Q.FxFzeOwc7wZ9.O32XMaiLrn0wW"
  },
  {
    "firstName": "Test",
    "lastName": "User30",
    "email": "user30@user.com",
    "password": "$2b$10$wO9ozl5LLGmLQBnA1FWv5.Mk8Q.FxFzeOwc7wZ9.O32XMaiLrn0wW"
  },
  {
    "firstName": "Test",
    "lastName": "User31",
    "email": "user31@user.com",
    "password": "$2b$10$wO9ozl5LLGmLQBnA1FWv5.Mk8Q.FxFzeOwc7wZ9.O32XMaiLrn0wW"
  },
  {
    "firstName": "Test",
    "lastName": "User32",
    "email": "user32@user.com",
    "password": "$2b$10$wO9ozl5LLGmLQBnA1FWv5.Mk8Q.FxFzeOwc7wZ9.O32XMaiLrn0wW"
  },
  {
    "firstName": "Test",
    "lastName": "User33",
    "email": "user33@user.com",
    "password": "$2b$10$wO9ozl5LLGmLQBnA1FWv5.Mk8Q.FxFzeOwc7wZ9.O32XMaiLrn0wW"
  },
  {
    "firstName": "Test",
    "lastName": "User34",
    "email": "user34@user.com",
    "password": "$2b$10$wO9ozl5LLGmLQBnA1FWv5.Mk8Q.FxFzeOwc7wZ9.O32XMaiLrn0wW"
  },
  {
    "firstName": "Test",
    "lastName": "User35",
    "email": "user35@user.com",
    "password": "$2b$10$wO9ozl5LLGmLQBnA1FWv5.Mk8Q.FxFzeOwc7wZ9.O32XMaiLrn0wW"
  },
  {
    "firstName": "Test",
    "lastName": "User36",
    "email": "user36@user.com",
    "password": "$2b$10$wO9ozl5LLGmLQBnA1FWv5.Mk8Q.FxFzeOwc7wZ9.O32XMaiLrn0wW"
  },
  {
    "firstName": "Test",
    "lastName": "User37",
    "email": "user37@user.com",
    "password": "$2b$10$wO9ozl5LLGmLQBnA1FWv5.Mk8Q.FxFzeOwc7wZ9.O32XMaiLrn0wW"
  },
  {
    "firstName": "Test",
    "lastName": "User38",
    "email": "user38@user.com",
    "password": "$2b$10$wO9ozl5LLGmLQBnA1FWv5.Mk8Q.FxFzeOwc7wZ9.O32XMaiLrn0wW"
  },
  {
    "firstName": "Test",
    "lastName": "User39",
    "email": "user39@user.com",
    "password": "$2b$10$wO9ozl5LLGmLQBnA1FWv5.Mk8Q.FxFzeOwc7wZ9.O32XMaiLrn0wW"
  },
  {
    "firstName": "Test",
    "lastName": "User40",
    "email": "user40@user.com",
    "password": "$2b$10$wO9ozl5LLGmLQBnA1FWv5.Mk8Q.FxFzeOwc7wZ9.O32XMaiLrn0wW"
  },
  {
    "firstName": "Test",
    "lastName": "User41",
    "email": "user41@user.com",
    "password": "$2b$10$wO9ozl5LLGmLQBnA1FWv5.Mk8Q.FxFzeOwc7wZ9.O32XMaiLrn0wW"
  },
  {
    "firstName": "Test",
    "lastName": "User42",
    "email": "user42@user.com",
    "password": "$2b$10$wO9ozl5LLGmLQBnA1FWv5.Mk8Q.FxFzeOwc7wZ9.O32XMaiLrn0wW"
  },
  {
    "firstName": "Test",
    "lastName": "User43",
    "email": "user43@user.com",
    "password": "$2b$10$wO9ozl5LLGmLQBnA1FWv5.Mk8Q.FxFzeOwc7wZ9.O32XMaiLrn0wW"
  },
  {
    "firstName": "Test",
    "lastName": "User44",
    "email": "user44@user.com",
    "password": "$2b$10$wO9ozl5LLGmLQBnA1FWv5.Mk8Q.FxFzeOwc7wZ9.O32XMaiLrn0wW"
  },
  {
    "firstName": "Test",
    "lastName": "User45",
    "email": "user45@user.com",
    "password": "$2b$10$wO9ozl5LLGmLQBnA1FWv5.Mk8Q.FxFzeOwc7wZ9.O32XMaiLrn0wW"
  },
  {
    "firstName": "Test",
    "lastName": "User46",
    "email": "user46@user.com",
    "password": "$2b$10$wO9ozl5LLGmLQBnA1FWv5.Mk8Q.FxFzeOwc7wZ9.O32XMaiLrn0wW"
  },
  {
    "firstName": "Test",
    "lastName": "User47",
    "email": "user47@user.com",
    "password": "$2b$10$wO9ozl5LLGmLQBnA1FWv5.Mk8Q.FxFzeOwc7wZ9.O32XMaiLrn0wW"
  },
  {
    "firstName": "Test",
    "lastName": "User48",
    "email": "user48@user.com",
    "password": "$2b$10$wO9ozl5LLGmLQBnA1FWv5.Mk8Q.FxFzeOwc7wZ9.O32XMaiLrn0wW"
  },
  {
    "firstName": "Test",
    "lastName": "User49",
    "email": "user49@user.com",
    "password": "$2b$10$wO9ozl5LLGmLQBnA1FWv5.Mk8Q.FxFzeOwc7wZ9.O32XMaiLrn0wW"
  },
  {
    "firstName": "Test",
    "lastName": "User50",
    "email": "user50@user.com",
    "password": "$2b$10$wO9ozl5LLGmLQBnA1FWv5.Mk8Q.FxFzeOwc7wZ9.O32XMaiLrn0wW"
  },
  {
    "firstName": "Test",
    "lastName": "User51",
    "email": "user51@user.com",
    "password": "$2b$10$wO9ozl5LLGmLQBnA1FWv5.Mk8Q.FxFzeOwc7wZ9.O32XMaiLrn0wW"
  },
  {
    "firstName": "Test",
    "lastName": "User52",
    "email": "user52@user.com",
    "password": "$2b$10$wO9ozl5LLGmLQBnA1FWv5.Mk8Q.FxFzeOwc7wZ9.O32XMaiLrn0wW"
  },
  {
    "firstName": "Test",
    "lastName": "User53",
    "email": "user53@user.com",
    "password": "$2b$10$wO9ozl5LLGmLQBnA1FWv5.Mk8Q.FxFzeOwc7wZ9.O32XMaiLrn0wW"
  },
  {
    "firstName": "Test",
    "lastName": "User54",
    "email": "user54@user.com",
    "password": "$2b$10$wO9ozl5LLGmLQBnA1FWv5.Mk8Q.FxFzeOwc7wZ9.O32XMaiLrn0wW"
  },
  {
    "firstName": "Test",
    "lastName": "User55",
    "email": "user55@user.com",
    "password": "$2b$10$wO9ozl5LLGmLQBnA1FWv5.Mk8Q.FxFzeOwc7wZ9.O32XMaiLrn0wW"
  },
  {
    "firstName": "Test",
    "lastName": "User56",
    "email": "user56@user.com",
    "password": "$2b$10$wO9ozl5LLGmLQBnA1FWv5.Mk8Q.FxFzeOwc7wZ9.O32XMaiLrn0wW"
  },
  {
    "firstName": "Test",
    "lastName": "User57",
    "email": "user57@user.com",
    "password": "$2b$10$wO9ozl5LLGmLQBnA1FWv5.Mk8Q.FxFzeOwc7wZ9.O32XMaiLrn0wW"
  },
  {
    "firstName": "Test",
    "lastName": "User58",
    "email": "user58@user.com",
    "password": "$2b$10$wO9ozl5LLGmLQBnA1FWv5.Mk8Q.FxFzeOwc7wZ9.O32XMaiLrn0wW"
  },
  {
    "firstName": "Test",
    "lastName": "User59",
    "email": "user59@user.com",
    "password": "$2b$10$wO9ozl5LLGmLQBnA1FWv5.Mk8Q.FxFzeOwc7wZ9.O32XMaiLrn0wW"
  },
  {
    "firstName": "Test",
    "lastName": "User60",
    "email": "user60@user.com",
    "password": "$2b$10$wO9ozl5LLGmLQBnA1FWv5.Mk8Q.FxFzeOwc7wZ9.O32XMaiLrn0wW"
  },
  {
    "firstName": "Test",
    "lastName": "User61",
    "email": "user61@user.com",
    "password": "$2b$10$wO9ozl5LLGmLQBnA1FWv5.Mk8Q.FxFzeOwc7wZ9.O32XMaiLrn0wW"
  },
  {
    "firstName": "Test",
    "lastName": "User62",
    "email": "user62@user.com",
    "password": "$2b$10$wO9ozl5LLGmLQBnA1FWv5.Mk8Q.FxFzeOwc7wZ9.O32XMaiLrn0wW"
  },
  {
    "firstName": "Test",
    "lastName": "User63",
    "email": "user63@user.com",
    "password": "$2b$10$wO9ozl5LLGmLQBnA1FWv5.Mk8Q.FxFzeOwc7wZ9.O32XMaiLrn0wW"
  },
  {
    "firstName": "Test",
    "lastName": "User64",
    "email": "user64@user.com",
    "password": "$2b$10$wO9ozl5LLGmLQBnA1FWv5.Mk8Q.FxFzeOwc7wZ9.O32XMaiLrn0wW"
  },
  {
    "firstName": "Test",
    "lastName": "User65",
    "email": "user65@user.com",
    "password": "$2b$10$wO9ozl5LLGmLQBnA1FWv5.Mk8Q.FxFzeOwc7wZ9.O32XMaiLrn0wW"
  },
  {
    "firstName": "Test",
    "lastName": "User66",
    "email": "user66@user.com",
    "password": "$2b$10$wO9ozl5LLGmLQBnA1FWv5.Mk8Q.FxFzeOwc7wZ9.O32XMaiLrn0wW"
  },
  {
    "firstName": "Test",
    "lastName": "User67",
    "email": "user67@user.com",
    "password": "$2b$10$wO9ozl5LLGmLQBnA1FWv5.Mk8Q.FxFzeOwc7wZ9.O32XMaiLrn0wW"
  },
  {
    "firstName": "Test",
    "lastName": "User68",
    "email": "user68@user.com",
    "password": "$2b$10$wO9ozl5LLGmLQBnA1FWv5.Mk8Q.FxFzeOwc7wZ9.O32XMaiLrn0wW"
  },
  {
    "firstName": "Test",
    "lastName": "User69",
    "email": "user69@user.com",
    "password": "$2b$10$wO9ozl5LLGmLQBnA1FWv5.Mk8Q.FxFzeOwc7wZ9.O32XMaiLrn0wW"
  },
  {
    "firstName": "Test",
    "lastName": "User70",
    "email": "user70@user.com",
    "password": "$2b$10$wO9ozl5LLGmLQBnA1FWv5.Mk8Q.FxFzeOwc7wZ9.O32XMaiLrn0wW"
  },
  {
    "firstName": "Test",
    "lastName": "User71",
    "email": "user71@user.com",
    "password": "$2b$10$wO9ozl5LLGmLQBnA1FWv5.Mk8Q.FxFzeOwc7wZ9.O32XMaiLrn0wW"
  },
  {
    "firstName": "Test",
    "lastName": "User72",
    "email": "user72@user.com",
    "password": "$2b$10$wO9ozl5LLGmLQBnA1FWv5.Mk8Q.FxFzeOwc7wZ9.O32XMaiLrn0wW"
  },
  {
    "firstName": "Test",
    "lastName": "User73",
    "email": "user73@user.com",
    "password": "$2b$10$wO9ozl5LLGmLQBnA1FWv5.Mk8Q.FxFzeOwc7wZ9.O32XMaiLrn0wW"
  },
  {
    "firstName": "Test",
    "lastName": "User74",
    "email": "user74@user.com",
    "password": "$2b$10$wO9ozl5LLGmLQBnA1FWv5.Mk8Q.FxFzeOwc7wZ9.O32XMaiLrn0wW"
  },
  {
    "firstName": "Test",
    "lastName": "User75",
    "email": "user75@user.com",
    "password": "$2b$10$wO9ozl5LLGmLQBnA1FWv5.Mk8Q.FxFzeOwc7wZ9.O32XMaiLrn0wW"
  },
  {
    "firstName": "Test",
    "lastName": "User76",
    "email": "user76@user.com",
    "password": "$2b$10$wO9ozl5LLGmLQBnA1FWv5.Mk8Q.FxFzeOwc7wZ9.O32XMaiLrn0wW"
  },
  {
    "firstName": "Test",
    "lastName": "User77",
    "email": "user77@user.com",
    "password": "$2b$10$wO9ozl5LLGmLQBnA1FWv5.Mk8Q.FxFzeOwc7wZ9.O32XMaiLrn0wW"
  },
  {
    "firstName": "Test",
    "lastName": "User78",
    "email": "user78@user.com",
    "password": "$2b$10$wO9ozl5LLGmLQBnA1FWv5.Mk8Q.FxFzeOwc7wZ9.O32XMaiLrn0wW"
  },
  {
    "firstName": "Test",
    "lastName": "User79",
    "email": "user79@user.com",
    "password": "$2b$10$wO9ozl5LLGmLQBnA1FWv5.Mk8Q.FxFzeOwc7wZ9.O32XMaiLrn0wW"
  },
  {
    "firstName": "Test",
    "lastName": "User80",
    "email": "user80@user.com",
    "password": "$2b$10$wO9ozl5LLGmLQBnA1FWv5.Mk8Q.FxFzeOwc7wZ9.O32XMaiLrn0wW"
  },
  {
    "firstName": "Test",
    "lastName": "User81",
    "email": "user81@user.com",
    "password": "$2b$10$wO9ozl5LLGmLQBnA1FWv5.Mk8Q.FxFzeOwc7wZ9.O32XMaiLrn0wW"
  },
  {
    "firstName": "Test",
    "lastName": "User82",
    "email": "user82@user.com",
    "password": "$2b$10$wO9ozl5LLGmLQBnA1FWv5.Mk8Q.FxFzeOwc7wZ9.O32XMaiLrn0wW"
  },
  {
    "firstName": "Test",
    "lastName": "User83",
    "email": "user83@user.com",
    "password": "$2b$10$wO9ozl5LLGmLQBnA1FWv5.Mk8Q.FxFzeOwc7wZ9.O32XMaiLrn0wW"
  },
  {
    "firstName": "Test",
    "lastName": "User84",
    "email": "user84@user.com",
    "password": "$2b$10$wO9ozl5LLGmLQBnA1FWv5.Mk8Q.FxFzeOwc7wZ9.O32XMaiLrn0wW"
  },
  {
    "firstName": "Test",
    "lastName": "User85",
    "email": "user85@user.com",
    "password": "$2b$10$wO9ozl5LLGmLQBnA1FWv5.Mk8Q.FxFzeOwc7wZ9.O32XMaiLrn0wW"
  },
  {
    "firstName": "Test",
    "lastName": "User86",
    "email": "user86@user.com",
    "password": "$2b$10$wO9ozl5LLGmLQBnA1FWv5.Mk8Q.FxFzeOwc7wZ9.O32XMaiLrn0wW"
  },
  {
    "firstName": "Test",
    "lastName": "User87",
    "email": "user87@user.com",
    "password": "$2b$10$wO9ozl5LLGmLQBnA1FWv5.Mk8Q.FxFzeOwc7wZ9.O32XMaiLrn0wW"
  },
  {
    "firstName": "Test",
    "lastName": "User88",
    "email": "user88@user.com",
    "password": "$2b$10$wO9ozl5LLGmLQBnA1FWv5.Mk8Q.FxFzeOwc7wZ9.O32XMaiLrn0wW"
  },
  {
    "firstName": "Test",
    "lastName": "User89",
    "email": "user89@user.com",
    "password": "$2b$10$wO9ozl5LLGmLQBnA1FWv5.Mk8Q.FxFzeOwc7wZ9.O32XMaiLrn0wW"
  },
  {
    "firstName": "Test",
    "lastName": "User90",
    "email": "user90@user.com",
    "password": "$2b$10$wO9ozl5LLGmLQBnA1FWv5.Mk8Q.FxFzeOwc7wZ9.O32XMaiLrn0wW"
  }
]
